tunnelossh/__init__.py
tunnelossh/main.py
tunnelossh-0.1.6.dist-info/LICENSE
tunnelossh-0.1.6.dist-info/METADATA
tunnelossh-0.1.6.dist-info/WHEEL
tunnelossh-0.1.6.dist-info/top_level.txt
tunnelossh-0.1.6.dist-info/RECORD
